commander/__init__.py
commander/cli.py
commander/spinner.py
commander/ssh.py
commander/util.py
slicecommander-0.2.post1.dist-info/licenses/LICENSE
slicecommander-0.2.post1.dist-info/METADATA
slicecommander-0.2.post1.dist-info/WHEEL
slicecommander-0.2.post1.dist-info/entry_points.txt
slicecommander-0.2.post1.dist-info/top_level.txt
slicecommander-0.2.post1.dist-info/RECORD
