Metadata-Version: 2.4
Name: SliceCommander
Version: 0.2.post1
Summary: FABRIC Slice Commander
Home-page: https://github.com/fabric-testbed/slice-commander
Author: Ezra Kissel
Keywords: fabric slice command
Classifier: Development Status :: 5 - Production/Stable
Classifier: Intended Audience :: Developers
Classifier: Topic :: Software Development :: Libraries :: Application Frameworks
Classifier: License :: OSI Approved :: BSD License
Classifier: Programming Language :: Python :: 3
License-File: LICENSE
Requires-Dist: fabrictestbed-extensions>=1.8.1
Requires-Dist: libtmux
Requires-Dist: ptyprocess
Requires-Dist: pygments
Requires-Dist: docopt
Dynamic: author
Dynamic: classifier
Dynamic: description
Dynamic: description-content-type
Dynamic: home-page
Dynamic: keywords
Dynamic: license-file
Dynamic: requires-dist
Dynamic: summary
